bloomfilter/__init__.py
bloomfilter/bloomfilter.py
bloomfilter/bloomfilter_strategy.py
bloomfilter_py-1.1.0.dist-info/LICENSE
bloomfilter_py-1.1.0.dist-info/METADATA
bloomfilter_py-1.1.0.dist-info/WHEEL
bloomfilter_py-1.1.0.dist-info/top_level.txt
bloomfilter_py-1.1.0.dist-info/RECORD
