Metadata-Version: 2.1
Name: bloomfilter-py
Version: 1.1.0
Summary: Yet another bloomfilter implementation in Python
Author-email: OldPanda <me@old-panda.com>
License: MIT License
Project-URL: Documentation, https://github.com/OldPanda/bloomfilter-py/blob/master/README.md
Project-URL: Homepage, https://github.com/OldPanda/bloomfilter-py
Project-URL: Repository, https://github.com/OldPanda/bloomfilter-py.git
Keywords: bloomfilter
Classifier: Development Status :: 5 - Production/Stable
Classifier: Intended Audience :: Developers
Classifier: License :: OSI Approved :: MIT License
Classifier: Programming Language :: Python
Classifier: Programming Language :: Python :: 3
Classifier: Programming Language :: Python :: 3.8
Classifier: Programming Language :: Python :: 3.9
Classifier: Programming Language :: Python :: 3.10
Classifier: Programming Language :: Python :: 3.11
Classifier: Programming Language :: Python :: 3.12
Classifier: Operating System :: OS Independent
Classifier: Topic :: Software Development :: Libraries :: Python Modules
Requires-Python: >=3.8
License-File: LICENSE
Requires-Dist: bitarray==2.9.2
Requires-Dist: mmh3==4.1.0
